syntia_term/__init__.py
syntia_term/app.py
syntia_term/run.py
syntia_term/components/__init__.py
syntia_term/components/horizontal_splitter.py
syntia_term/components/tabbed_right_panel.py
syntia_term/components/tabbed_text_area.py
syntia_term/components/terminal.py
syntia_term/components/vertical_splitter.py
syntia_term-0.0.5.dist-info/METADATA
syntia_term-0.0.5.dist-info/WHEEL
syntia_term-0.0.5.dist-info/entry_points.txt
syntia_term-0.0.5.dist-info/licenses/LICENSE
syntia_term-0.0.5.dist-info/RECORD
