Metadata-Version: 2.4
Name: syntia_term
Version: 0.0.5
Summary: A minimal IDE for your terminal
License-File: LICENSE
Requires-Python: >=3.12
Requires-Dist: pyte>=0.8.2
Requires-Dist: textual[syntax]>=6.0.0
Requires-Dist: weave>=0.52.5
